turbo_package.cpython-311-darwin.so
slow_package/__init__.py
slow_package/slow_functions.py
turbo_code-0.0.1.dist-info/LICENSE
turbo_code-0.0.1.dist-info/METADATA
turbo_code-0.0.1.dist-info/WHEEL
turbo_code-0.0.1.dist-info/top_level.txt
turbo_code-0.0.1.dist-info/RECORD
