Metadata-Version: 2.1
Name: turbo-code
Version: 0.0.1
Home-page: https://github.com/Alexander-Nasuta/pybind11_example_with_tox_testing
Author: Alexander Nasuta
Author-email: Alexander Nasuta <alexander.nasuta@ima.rwth-aachen.de>
License: Copyright (c) 2016 The Pybind Development Team, All rights reserved.
Classifier: License :: OSI Approved :: MIT License
Classifier: Programming Language :: Python
Classifier: Programming Language :: Python :: 3
Requires-Python: >=3.11
License-File: LICENSE
Requires-Dist: numpy
Provides-Extra: dev
Requires-Dist: pip-tools ; extra == 'dev'
Requires-Dist: pytest ; extra == 'dev'
Requires-Dist: pytest-cov ; extra == 'dev'
Requires-Dist: tox ; extra == 'dev'
Requires-Dist: twine ; extra == 'dev'
Requires-Dist: sphinx ; extra == 'dev'
Requires-Dist: furo ; extra == 'dev'
Provides-Extra: test
Requires-Dist: pytest ; extra == 'test'
